{
  "url": "https://freesound.org/people/looplicator/",
  "username": "looplicator",
  "about": "I create loops and beats with an industrial, ambient, and cinematic flair, often imbued with a dark and futuristic ambiance.\n\nInstagram: <a href=\"https://www.instagram.com/looplicator/\" rel=\"nofollow\">https://www.instagram.com/looplicator/</a>\nBandcamp: <a href=\"https://looplicator.bandcamp.com/\" rel=\"nofollow\">https://looplicator.bandcamp.com/</a>\nSoundcloud: <a href=\"https://soundcloud.com/looplicator\" rel=\"nofollow\">https://soundcloud.com/looplicator</a>",
  "home_page": "https://www.youtube.com/@looplicator",
  "avatar": {
    "small": "https://freesound.org/data/avatars/12880/12880153_S.jpg",
    "medium": "https://freesound.org/data/avatars/12880/12880153_M.jpg",
    "large": "https://freesound.org/data/avatars/12880/12880153_L.jpg"
  },
  "date_joined": "2021-05-11T20:49:33.102437+02:00",
  "num_sounds": 16318,
  "sounds": "https://freesound.org/apiv2/users/looplicator/sounds/",
  "num_packs": 188,
  "packs": "https://freesound.org/apiv2/users/looplicator/packs/",
  "num_posts": 0,
  "num_comments": 2
}